oxmltotxt/__init__.py
oxmltotxt/oxmltotxt.py
oxmltotxt-0.0.2.dist-info/LICENSE
oxmltotxt-0.0.2.dist-info/METADATA
oxmltotxt-0.0.2.dist-info/WHEEL
oxmltotxt-0.0.2.dist-info/top_level.txt
oxmltotxt-0.0.2.dist-info/RECORD
