Metadata-Version: 2.1
Name: oxmltotxt
Version: 0.0.2
Summary: A simple tool to extract text from Open XML format (.docx/.xlsx/.pptx). The tool is meant to be used in combination with git to facilitate the version control of Open XML files.
Author-email: Michael von den Driesch <mdriesch@web.de>
License: MIT
Project-URL: Homepage, https://github.com/mdriesch/oxmltotxt
Keywords: Open XML,version control,git,MS Excel
Classifier: Programming Language :: Python :: 3
Classifier: Programming Language :: Python :: 3.7
Classifier: Programming Language :: Python :: 3.8
Classifier: Programming Language :: Python :: 3.9
Classifier: Programming Language :: Python :: 3.10
Classifier: Topic :: Software Development :: Version Control :: Git
Classifier: Topic :: Software Development :: Libraries
Classifier: License :: OSI Approved :: MIT License
Classifier: Operating System :: OS Independent
Classifier: Development Status :: 3 - Alpha
Classifier: Environment :: Console
Requires-Python: >=3
License-File: LICENSE
Requires-Dist: beautifulsoup4
Requires-Dist: oletools
Requires-Dist: lxml
Provides-Extra: dev
Requires-Dist: pytest (>=3.7) ; extra == 'dev'
Requires-Dist: check-manifest ; extra == 'dev'
Requires-Dist: twine ; extra == 'dev'
Requires-Dist: black ; extra == 'dev'
Requires-Dist: flake8 ; extra == 'dev'
Requires-Dist: mypy ; extra == 'dev'
Requires-Dist: isort ; extra == 'dev'
Requires-Dist: bumpver ; extra == 'dev'
Requires-Dist: wheel ; extra == 'dev'
